IOTAIData/IOTDataProcessor.py
IOTAIData/IOTDataStructure.py
IOTAIData/__init__.py
IOTAIModel/IOTModelGenerator.py
IOTAIModel/__init__.py
IOTLibraryTestMode-0.0.0.2.dist-info/METADATA
IOTLibraryTestMode-0.0.0.2.dist-info/WHEEL
IOTLibraryTestMode-0.0.0.2.dist-info/top_level.txt
IOTLibraryTestMode-0.0.0.2.dist-info/RECORD
